pyreqmerger/__init__.py
pyreqmerger/console.py
pyreqmerger/enums.py
pyreqmerger/file_handler.py
pyreqmerger/main.py
pyreqmerger/merger.py
pyreqmerger/pyreq_parser.py
pyreqmerger/req_classes.py
pyreqmerger/version_file.py
pyreq_merger-0.0.3.dist-info/LICENSE.txt
pyreq_merger-0.0.3.dist-info/METADATA
pyreq_merger-0.0.3.dist-info/WHEEL
pyreq_merger-0.0.3.dist-info/entry_points.txt
pyreq_merger-0.0.3.dist-info/top_level.txt
pyreq_merger-0.0.3.dist-info/RECORD
