Metadata-Version: 2.1
Name: pyreq-merger
Version: 0.0.3
Summary: Merge 2 requirement files into a single file, using the specified method.
Home-page: https://github.com/mhristodor/pyreq-merger
Author: mhristodor
Author-email: minumh99@gmail.com
License: MIT
Project-URL: Documentation, https://github.com/mhristodor/pyreq-merger/blob/main/README.md
Project-URL: Source, https://github.com/mhristodor/pyreq-merger
Project-URL: Tracker, https://github.com/mhristodor/pyreq-merger/issues
Project-URL: Author, https://www.linkedin.com/in/mihail-hristodor-1174b2177/
Project-URL: Funding, https://www.buymeacoffee.com/m.hristodor
Keywords: requirements merge tool
Classifier: Development Status :: 3 - Alpha
Classifier: Intended Audience :: Developers
Classifier: License :: OSI Approved :: MIT License
Classifier: Programming Language :: Python :: 3.11
Requires-Python: >=3.11
License-File: LICENSE.txt
Requires-Dist: markdown-it-py ==3.0.0
Requires-Dist: mdurl ==0.1.2
Requires-Dist: pydocstyle ==6.3.0
Requires-Dist: Pygments ==2.16.1
Requires-Dist: rich ==13.5.3
Requires-Dist: snowballstemmer ==2.2.0
